aye/__init__.py
aye/__main__.py
aye/api.py
aye/auth.py
aye/completers.py
aye/config.py
aye/repl.py
aye/service.py
aye/snapshot.py
aye/source_collector.py
aye/ui.py
aye_cli-0.1.4.dist-info/licenses/LICENSE
aye_cli-0.1.4.dist-info/METADATA
aye_cli-0.1.4.dist-info/WHEEL
aye_cli-0.1.4.dist-info/entry_points.txt
aye_cli-0.1.4.dist-info/top_level.txt
aye_cli-0.1.4.dist-info/RECORD
