Metadata-Version: 2.4
Name: aye-cli
Version: 0.1.4
Summary: Aye: AI‑powered coding assistant for the terminal
Author-email: "Acrotron, Inc." <info@acrotron.com>
License: MIT
Requires-Python: >=3.8
License-File: LICENSE
Requires-Dist: typer[all]>=0.9.0
Requires-Dist: httpx>=0.27.0
Requires-Dist: keyring>=24.0.0
Requires-Dist: prompt-toolkit>=3.0.0
Provides-Extra: dev
Requires-Dist: pytest>=7.0; extra == "dev"
Requires-Dist: ruff>=0.6; extra == "dev"
Dynamic: license-file
